babalar/__init__.py
babalar/babalar.py
babalar-0.0.1.dist-info/licenses/LICENSE
babalar-0.0.1.dist-info/METADATA
babalar-0.0.1.dist-info/WHEEL
babalar-0.0.1.dist-info/top_level.txt
babalar-0.0.1.dist-info/RECORD
