Metadata-Version: 2.4
Name: babalar
Version: 0.0.1
Summary: PyPI Project for Python Programming Lecture
Author-email: Berke Alpaslan <210316016@ogr.cbu.edu.tr>
Project-URL: Homepage, https://github.com/BerkeAlpaslan/babalar
Keywords: babalar
Classifier: Development Status :: 3 - Alpha
Classifier: Intended Audience :: Developers
Classifier: License :: OSI Approved :: MIT License
Classifier: Programming Language :: Python :: 3
Classifier: Operating System :: OS Independent
Requires-Python: >=3.12
License-File: LICENSE
Dynamic: license-file
